errs_mcp_demo/__init__.py
errs_mcp_demo-0.1.0.dist-info/METADATA
errs_mcp_demo-0.1.0.dist-info/WHEEL
errs_mcp_demo-0.1.0.dist-info/entry_points.txt
errs_mcp_demo-0.1.0.dist-info/RECORD
